asynckivy/__init__.py
asynckivy/_anim_attrs.py
asynckivy/_anim_with_xxx.py
asynckivy/_etc.py
asynckivy/_event.py
asynckivy/_interpolate.py
asynckivy/_managed_start.py
asynckivy/_sleep.py
asynckivy/_smooth_attr.py
asynckivy/_threading.py
asynckivy/modal.py
asynckivy/transition.py
asynckivy-0.9.3.dist-info/WHEEL
asynckivy-0.9.3.dist-info/METADATA
asynckivy-0.9.3.dist-info/RECORD
